DownloadHelper.py
SourceDataHelper.py
moonss.py
moonss-0.114.dist-info/METADATA
moonss-0.114.dist-info/WHEEL
moonss-0.114.dist-info/top_level.txt
moonss-0.114.dist-info/RECORD
