Metadata-Version: 2.1
Name: moonss
Version: 0.114
Summary: A Des of moonss
Home-page: https://github.com/vtandroid/dokr
Author: Thanh Hoa
Author-email: thanhhoakhmt1@gmail.com
Classifier: Programming Language :: Python :: 3
Classifier: License :: OSI Approved :: MIT License
Classifier: Operating System :: OS Independent
Requires-Dist: requests==2.25.1
Requires-Dist: moviepy==1.0.3
Requires-Dist: Pillow==9.5.0
Requires-Dist: coolbg
Requires-Dist: gbak
Requires-Dist: yt_dlp
